openai_multi_tool_use_parallel_patch.py
openai_multi_tool_use_parallel_patch-0.2.0.dist-info/LICENSE
openai_multi_tool_use_parallel_patch-0.2.0.dist-info/METADATA
openai_multi_tool_use_parallel_patch-0.2.0.dist-info/WHEEL
openai_multi_tool_use_parallel_patch-0.2.0.dist-info/RECORD
