Metadata-Version: 2.1
Name: openai-multi-tool-use-parallel-patch
Version: 0.2.0
Summary: Quick monkey-patching fix for OpenAI's hallucinated multi_tool_use.parallel
License: MIT
Author: Philipp Dowling
Author-email: phdowling@users.noreply.github.com
Requires-Python: >=3.7.1,<4.0.0
Classifier: License :: OSI Approved :: MIT License
Classifier: Programming Language :: Python :: 3
Classifier: Programming Language :: Python :: 3.8
Classifier: Programming Language :: Python :: 3.9
Classifier: Programming Language :: Python :: 3.10
Classifier: Programming Language :: Python :: 3.11
Requires-Dist: openai (>=1.3.6,<2.0.0)
